three_d_converter/.DS_Store
three_d_converter/__init__.py
three_d_converter/blender_installation.py
three_d_converter/blender_scripts/__init__.py
three_d_converter/blender_scripts/exporter/__init__.py
three_d_converter/blender_scripts/exporter/base.py
three_d_converter/blender_scripts/exporter/factory.py
three_d_converter/blender_scripts/exporter/fbx.py
three_d_converter/blender_scripts/exporter/gltf_glb.py
three_d_converter/blender_scripts/exporter/obj.py
three_d_converter/blender_scripts/exporter/stl.py
three_d_converter/blender_scripts/exporter/usdz.py
three_d_converter/blender_scripts/exporter/x3d.py
three_d_converter/blender_scripts/filehandler/__init__.py
three_d_converter/blender_scripts/filehandler/filehandler.py
three_d_converter/blender_scripts/importer/__init__.py
three_d_converter/blender_scripts/importer/base.py
three_d_converter/blender_scripts/importer/factory.py
three_d_converter/blender_scripts/importer/fbx.py
three_d_converter/blender_scripts/importer/gltf_glb.py
three_d_converter/blender_scripts/importer/obj.py
three_d_converter/blender_scripts/importer/stl.py
three_d_converter/blender_scripts/importer/usdz.py
three_d_converter/blender_scripts/importer/x3d.py
three_d_converter/blender_scripts/main.py
three_d_converter/converter.py
three_d_converter-1.0.1.dist-info/METADATA
three_d_converter-1.0.1.dist-info/WHEEL
three_d_converter-1.0.1.dist-info/entry_points.txt
three_d_converter-1.0.1.dist-info/RECORD
