Metadata-Version: 2.1
Name: three_d_converter
Version: 1.0.1
Summary: 
Author: Ferhat Teker
Author-email: ferhat.teker@hotmail.de
Requires-Python: >=3.9,<4.0
Classifier: Programming Language :: Python :: 3
Classifier: Programming Language :: Python :: 3.9
Classifier: Programming Language :: Python :: 3.10
Classifier: Programming Language :: Python :: 3.11
Classifier: Programming Language :: Python :: 3.12
Requires-Dist: pylint (>=3.1.0,<4.0.0)
Requires-Dist: uuid (>=1.30,<2.0)
